[{
    "Drink Name": "Discover Kt",
    "Style": "",
    "Producer": "Apple Cottage",
    "Location": "Baldock, Hertfordshire",
    "ABV (%)": 4.6
  },
  {
    "Drink Name": "FTJ (Filthy Tramp Juice)",
    "Style": "",
    "Producer": "Apple Cottage",
    "Location": "Baldock, Hertfordshire",
    "ABV (%)": 6.7
  },
  {
    "Drink Name": "Gandhis FlipFlop",
    "Style": "",
    "Producer": "Apple Cottage",
    "Location": "Baldock, Hertfordshire",
    "ABV (%)": 6.7
  },
  {
    "Drink Name": "Kt (SV)",
    "Style": "",
    "Producer": "Apple Cottage",
    "Location": "Baldock, Hertfordshire",
    "ABV (%)": 5.6
  },
  {
    "Drink Name": "Pyder",
    "Style": "",
    "Producer": "Apple Cottage",
    "Location": "Baldock, Hertfordshire",
    "ABV (%)": 5
  },
  {
    "Drink Name": "Rum Cask",
    "Style": "",
    "Producer": "Apple Cottage",
    "Location": "Baldock, Hertfordshire",
    "ABV (%)": 5.5
  },
  {
    "Drink Name": "Special Branch",
    "Style": "",
    "Producer": "Apple Cottage",
    "Location": "Baldock, Hertfordshire",
    "ABV (%)": 5.4
  },
  {
    "Drink Name": "Warp Factor 7",
    "Style": "",
    "Producer": "Apple Cottage",
    "Location": "Baldock, Hertfordshire",
    "ABV (%)": 6.7
  },
  {
    "Drink Name": "Con-Cox-tion",
    "Style": "",
    "Producer": "Berties Cider Co.",
    "Location": "Braintree, Essex",
    "ABV (%)": 6.3
  },
  {
    "Drink Name": "Cox-in Cider (SV)",
    "Style": "",
    "Producer": "Berties Cider Co.",
    "Location": "Braintree, Essex",
    "ABV (%)": 7.5
  },
  {
    "Drink Name": "Discovered at 40 Dry (SV)",
    "Style": "",
    "Producer": "Berties Cider Co.",
    "Location": "Braintree, Essex",
    "ABV (%)": 6
  },
  {
    "Drink Name": "Discovered at 40 Medium (SV)",
    "Style": "",
    "Producer": "Berties Cider Co.",
    "Location": "Braintree, Essex",
    "ABV (%)": 6
  },
  {
    "Drink Name": "Elderflower",
    "Style": "",
    "Producer": "Berties Cider Co.",
    "Location": "Braintree, Essex",
    "ABV (%)": 4.5
  },
  {
    "Drink Name": "Galanthus Perry",
    "Style": "",
    "Producer": "Berties Cider Co.",
    "Location": "Braintree, Essex",
    "ABV (%)": 6
  },
  {
    "Drink Name": "OBSession",
    "Style": "",
    "Producer": "Berties Cider Co.",
    "Location": "Braintree, Essex",
    "ABV (%)": 4.5
  },
  {
    "Drink Name": "Pearf-Hic! Perry",
    "Style": "",
    "Producer": "Berties Cider Co.",
    "Location": "Braintree, Essex",
    "ABV (%)": 6.5
  },
  {
    "Drink Name": "Phoenix",
    "Style": "",
    "Producer": "Berties Cider Co.",
    "Location": "Braintree, Essex",
    "ABV (%)": 6.5
  },
  {
    "Drink Name": "Bushels",
    "Style": "",
    "Producer": "Biddendens",
    "Location": "Ashford, Kent",
    "ABV (%)": 6
  },
  {
    "Drink Name": "Red Love (SV)",
    "Style": "",
    "Producer": "Biddendens",
    "Location": "Ashford, Kent",
    "ABV (%)": 5
  },
  {
    "Drink Name": "Sweet",
    "Style": "",
    "Producer": "Big Bear Cider Mill",
    "Location": "Stisted, Essex",
    "ABV (%)": 4.8
  },
  {
    "Drink Name": "C2 (Cranberry & Cherry)",
    "Style": "",
    "Producer": "Bottle Kicking Cider Co.",
    "Location": "Hallaton, Leicestershire",
    "ABV (%)": 4
  },
  {
    "Drink Name": "C & L (Cranberry & Lime)",
    "Style": "",
    "Producer": "Bottle Kicking Cider Co.",
    "Location": "Hallaton, Leicestershire",
    "ABV (%)": 4
  },
  {
    "Drink Name": "Cross Farm Perry",
    "Style": "",
    "Producer": "Bottle Kicking Cider Co.",
    "Location": "Hallaton, Leicestershire",
    "ABV (%)": 5
  },
  {
    "Drink Name": "PPP (Pineapple, Peach & Passion Fruit)",
    "Style": "",
    "Producer": "Bottle Kicking Cider Co.",
    "Location": "Hallaton, Leicestershire",
    "ABV (%)": 4
  },
  {
    "Drink Name": "R & P (Raspberry & Pomegranate)",
    "Style": "",
    "Producer": "Bottle Kicking Cider Co.",
    "Location": "Hallaton, Leicestershire",
    "ABV (%)": 4
  },
  {
    "Drink Name": "Sweet Dreams",
    "Style": "",
    "Producer": "Buffoons",
    "Location": "Canewden, Essex",
    "ABV (%)": 6.5
  },
  {
    "Drink Name": "Griddle",
    "Style": "",
    "Producer": "Bumblebee Cider",
    "Location": "Somerset",
    "ABV (%)": 4.8
  },
  {
    "Drink Name": "Celtic Tiger (Orange & Pineapple)",
    "Style": "",
    "Producer": "Celtic Marches",
    "Location": "Bishops Frome, Herefordshire",
    "ABV (%)": 4
  },
  {
    "Drink Name": "Cracklin' Rosie Perry",
    "Style": "",
    "Producer": "Celtic Marches",
    "Location": "Bishops Frome, Herefordshire",
    "ABV (%)": 4.5
  },
  {
    "Drink Name": "Lily The Pink",
    "Style": "",
    "Producer": "Celtic Marches",
    "Location": "Bishops Frome, Herefordshire",
    "ABV (%)": 4.5
  },
  {
    "Drink Name": "Loubi Lou (Pomegranate & Rose)",
    "Style": "",
    "Producer": "Celtic Marches",
    "Location": "Bishops Frome, Herefordshire",
    "ABV (%)": 4
  },
  {
    "Drink Name": "Ruby Tuesday (Raspberry)",
    "Style": "",
    "Producer": "Celtic Marches",
    "Location": "Bishops Frome, Herefordshire",
    "ABV (%)": 4
  },
  {
    "Drink Name": "Pear",
    "Style": "",
    "Producer": "Cornish Orchards",
    "Location": "Duloe, Cornwall",
    "ABV (%)": 5
  },
  {
    "Drink Name": "Muscle Mary (Raspberry)",
    "Style": "",
    "Producer": "Cotswold Cider Co.",
    "Location": "Coleshill, Oxfordshire",
    "ABV (%)": 4
  },
  {
    "Drink Name": "Old Norfolk (Organic)",
    "Style": "",
    "Producer": "Crones",
    "Location": "Kenninghall, Norfolk",
    "ABV (%)": 7.5
  },
  {
    "Drink Name": "Perry (Organic)",
    "Style": "",
    "Producer": "Crones",
    "Location": "Kenninghall, Norfolk",
    "ABV (%)": 6
  },
  {
    "Drink Name": "Rum Cask (Organic)",
    "Style": "",
    "Producer": "Crones",
    "Location": "Kenninghall, Norfolk",
    "ABV (%)": 7.5
  },
  {
    "Drink Name": "User Friendly (Organic)",
    "Style": "",
    "Producer": "Crones",
    "Location": "Kenninghall, Norfolk",
    "ABV (%)": 6.2
  },
  {
    "Drink Name": "Cider with Rosemary",
    "Style": "",
    "Producer": "Delvin End",
    "Location": "Sible Hedingham, Essex",
    "ABV (%)": 7
  },
  {
    "Drink Name": "Storm",
    "Style": "",
    "Producer": "Delvin End",
    "Location": "Sible Hedingham, Essex",
    "ABV (%)": 7
  },
  {
    "Drink Name": "Summer Festival",
    "Style": "",
    "Producer": "Delvin End",
    "Location": "Sible Hedingham, Essex",
    "ABV (%)": 7
  },
  {
    "Drink Name": "Honey Bubble (Honey)",
    "Style": "",
    "Producer": "Dorset Nectar",
    "Location": "Waytown, Dorset",
    "ABV (%)": 4
  },
  {
    "Drink Name": "Impeared Vision",
    "Style": "",
    "Producer": "Double Vision",
    "Location": "Maidstone, Kent",
    "ABV (%)": 7.2
  },
  {
    "Drink Name": "Medium",
    "Style": "",
    "Producer": "Double Vision",
    "Location": "Maidstone, Kent",
    "ABV (%)": 7.2
  },
  {
    "Drink Name": "Strawberry",
    "Style": "",
    "Producer": "Double Vision",
    "Location": "Maidstone, Kent",
    "ABV (%)": 5.2
  },
  {
    "Drink Name": "Pear O Duddas",
    "Style": "",
    "Producer": "Dudda's Tun",
    "Location": "Doddington, Kent",
    "ABV (%)": 5.5
  },
  {
    "Drink Name": "Sweet Apple",
    "Style": "",
    "Producer": "Dudda's Tun",
    "Location": "Doddington, Kent",
    "ABV (%)": 5.5
  },
  {
    "Drink Name": "Rhubarb Bob (Rhubarb)",
    "Style": "",
    "Producer": "Farmer Jim's",
    "Location": "Torquay, Devon",
    "ABV (%)": 4
  },
  {
    "Drink Name": "Vintage Garden Cider Medium",
    "Style": "",
    "Producer": "Garden Cider Company",
    "Location": "Chiddinfold, Surrey",
    "ABV (%)": 6
  },
  {
    "Drink Name": "Elderflower",
    "Style": "",
    "Producer": "Garden Cider Company",
    "Location": "Chiddinfold, Surrey",
    "ABV (%)": 4
  },
  {
    "Drink Name": "Rum Tiddly Tum",
    "Style": "",
    "Producer": "Green Valley Cyder",
    "Location": "Exeter, Devon",
    "ABV (%)": 7.5
  },
  {
    "Drink Name": "Vintage",
    "Style": "",
    "Producer": "Green Valley Cyder",
    "Location": "Exeter, Devon",
    "ABV (%)": 7.5
  },
  {
    "Drink Name": "Farmhouse Perry",
    "Style": "",
    "Producer": "Gwatkins",
    "Location": "Abbeydore, Herefordshire",
    "ABV (%)": 7
  },
  {
    "Drink Name": "Squeal Pig Perry",
    "Style": "",
    "Producer": "Gwatkins",
    "Location": "Abbeydore, Herefordshire",
    "ABV (%)": 4.5
  },
  {
    "Drink Name": "Black Dragon",
    "Style": "",
    "Producer": "Gwynt Y Ddraig",
    "Location": "Llantwit Fardre, Glamorganshire",
    "ABV (%)": 7.2
  },
  {
    "Drink Name": "Farmyard Pyder",
    "Style": "",
    "Producer": "Gwynt Y Ddraig",
    "Location": "Llantwit Fardre, Glamorganshire",
    "ABV (%)": 6
  },
  {
    "Drink Name": "Happy Daze",
    "Style": "",
    "Producer": "Gwynt Y Ddraig",
    "Location": "Llantwit Fardre, Glamorganshire",
    "ABV (%)": 4.5
  },
  {
    "Drink Name": "Two Trees Perry",
    "Style": "",
    "Producer": "Gwynt Y Ddraig",
    "Location": "Llantwit Fardre, Glamorganshire",
    "ABV (%)": 4.5
  },
  {
    "Drink Name": "Dirty Harry's (Raspberry & Blackcurrant)",
    "Style": "",
    "Producer": "Harry's Cider",
    "Location": "Long Sutton, Somerset",
    "ABV (%)": 4
  },
  {
    "Drink Name": "Flash Harry's (Mango & Lime)",
    "Style": "",
    "Producer": "Harry's Cider",
    "Location": "Long Sutton, Somerset",
    "ABV (%)": 4
  },
  {
    "Drink Name": "No. 8",
    "Style": "",
    "Producer": "Harry's Cider",
    "Location": "Long Sutton, Somerset",
    "ABV (%)": 6.2
  },
  {
    "Drink Name": "Prince Harry's (Ginger)",
    "Style": "",
    "Producer": "Harry's Cider",
    "Location": "Long Sutton, Somerset",
    "ABV (%)": 4
  },
  {
    "Drink Name": "Scrummage",
    "Style": "",
    "Producer": "Harry's Cider",
    "Location": "Long Sutton, Somerset",
    "ABV (%)": 6.2
  },
  {
    "Drink Name": "Apple Cider",
    "Style": "",
    "Producer": "Hawkes",
    "Location": "London",
    "ABV (%)": 4.5
  },
  {
    "Drink Name": "Mixed Berry",
    "Style": "",
    "Producer": "Hawkes",
    "Location": "London",
    "ABV (%)": 4
  },
  {
    "Drink Name": "Tally Ho!",
    "Style": "",
    "Producer": "Hill Holme",
    "Location": "Great Totham, Essex",
    "ABV (%)": 5.5
  },
  {
    "Drink Name": "Blend 23",
    "Style": "",
    "Producer": "Kent Cider Co",
    "Location": "Canterbury, Kent",
    "ABV (%)": 6
  },
  {
    "Drink Name": "Elderflower",
    "Style": "",
    "Producer": "Kent Cider Co",
    "Location": "Canterbury, Kent",
    "ABV (%)": 5.5
  },
  {
    "Drink Name": "Pear",
    "Style": "",
    "Producer": "Kent Cider Co",
    "Location": "Canterbury, Kent",
    "ABV (%)": 6
  },
  {
    "Drink Name": "Rhubarb",
    "Style": "",
    "Producer": "Kent Cider Co",
    "Location": "Canterbury, Kent",
    "ABV (%)": 5.5
  },
  {
    "Drink Name": "Strawberry",
    "Style": "",
    "Producer": "Kent Cider Co",
    "Location": "Canterbury, Kent",
    "ABV (%)": 5.5
  },
  {
    "Drink Name": "Toffee Apple",
    "Style": "",
    "Producer": "Kent Cider Co",
    "Location": "Canterbury, Kent",
    "ABV (%)": 5.5
  },
  {
    "Drink Name": "Pear & Russet",
    "Style": "",
    "Producer": "Kentish Pip",
    "Location": "Canterbury, Kent",
    "ABV (%)": 6.5
  },
  {
    "Drink Name": "Pure Discovery",
    "Style": "",
    "Producer": "Kentish Pip",
    "Location": "Canterbury, Kent",
    "ABV (%)": 5.5
  },
  {
    "Drink Name": "Apples & Blackberry",
    "Style": "",
    "Producer": "Lilleys",
    "Location": "Frome, Somerset",
    "ABV (%)": 4
  },
  {
    "Drink Name": "Apples & Pears",
    "Style": "",
    "Producer": "Lilleys",
    "Location": "Frome, Somerset",
    "ABV (%)": 5.2
  },
  {
    "Drink Name": "Bee Sting",
    "Style": "",
    "Producer": "Lilleys",
    "Location": "Frome, Somerset",
    "ABV (%)": 7.5
  },
  {
    "Drink Name": "Crazy Goat",
    "Style": "",
    "Producer": "Lilleys",
    "Location": "Frome, Somerset",
    "ABV (%)": 6.8
  },
  {
    "Drink Name": "Darkcider",
    "Style": "",
    "Producer": "Lilleys",
    "Location": "Frome, Somerset",
    "ABV (%)": 7.5
  },
  {
    "Drink Name": "Pear & Raspberry",
    "Style": "",
    "Producer": "Lilleys",
    "Location": "Frome, Somerset",
    "ABV (%)": 4
  },
  {
    "Drink Name": "Pickled Parrot Perry",
    "Style": "",
    "Producer": "Lilleys",
    "Location": "Frome, Somerset",
    "ABV (%)": 6
  },
  {
    "Drink Name": "Red Rabbit",
    "Style": "",
    "Producer": "Lilleys",
    "Location": "Frome, Somerset",
    "ABV (%)": 6
  },
  {
    "Drink Name": "Rhubarb",
    "Style": "",
    "Producer": "Lilleys",
    "Location": "Frome, Somerset",
    "ABV (%)": 4
  },
  {
    "Drink Name": "Wild Dog",
    "Style": "",
    "Producer": "Lilleys",
    "Location": "Frome, Somerset",
    "ABV (%)": 7.5
  },
  {
    "Drink Name": "Medium Dry",
    "Style": "",
    "Producer": "London Glider",
    "Location": "Epping Green, Essex",
    "ABV (%)": 5.5
  },
  {
    "Drink Name": "Chalk Stream",
    "Style": "",
    "Producer": "Meon Valley Cider",
    "Location": "West Meon, Hampshire",
    "ABV (%)": 6
  },
  {
    "Drink Name": "Heron's Crest",
    "Style": "",
    "Producer": "Meon Valley Cider",
    "Location": "West Meon, Hampshire",
    "ABV (%)": 5
  },
  {
    "Drink Name": "Apples & Pears",
    "Style": "",
    "Producer": "Mr Whitehead's",
    "Location": "Alton, Hampshire",
    "ABV (%)": 5
  },
  {
    "Drink Name": "Cirrus Minor",
    "Style": "",
    "Producer": "Mr Whitehead's",
    "Location": "Alton, Hampshire",
    "ABV (%)": 5
  },
  {
    "Drink Name": "Equinox",
    "Style": "",
    "Producer": "Mr Whitehead's",
    "Location": "Alton, Hampshire",
    "ABV (%)": 4.5
  },
  {
    "Drink Name": "Hampshire Perry",
    "Style": "",
    "Producer": "Mr Whitehead's",
    "Location": "Alton, Hampshire",
    "ABV (%)": 3.8
  },
  {
    "Drink Name": "Midnight Special Perry",
    "Style": "",
    "Producer": "Mr Whitehead's",
    "Location": "Alton, Hampshire",
    "ABV (%)": 5
  },
  {
    "Drink Name": "Novo Pyrus Perry",
    "Style": "",
    "Producer": "Mr Whitehead's",
    "Location": "Alton, Hampshire",
    "ABV (%)": 7
  },
  {
    "Drink Name": "Plum Cider",
    "Style": "",
    "Producer": "Mr Whitehead's",
    "Location": "Alton, Hampshire",
    "ABV (%)": 4
  },
  {
    "Drink Name": "Strawberry Cider",
    "Style": "",
    "Producer": "Mr Whitehead's",
    "Location": "Alton, Hampshire",
    "ABV (%)": 4
  },
  {
    "Drink Name": "Hillside Haze",
    "Style": "",
    "Producer": "Napton Cidery",
    "Location": "Napton, Warwickshire",
    "ABV (%)": 5.3
  },
  {
    "Drink Name": "Single Tree Perry (SV)",
    "Style": "",
    "Producer": "Napton Cidery",
    "Location": "Napton, Warwickshire",
    "ABV (%)": 5.2
  },
  {
    "Drink Name": "Vintage",
    "Style": "",
    "Producer": "Napton Cidery",
    "Location": "Napton, Warwickshire",
    "ABV (%)": 4.6
  },
  {
    "Drink Name": "Piglet's Choice Perry",
    "Style": "",
    "Producer": "Nempnett",
    "Location": "Nempnett Thrubwell, Somerset",
    "ABV (%)": 7
  },
  {
    "Drink Name": "Perry",
    "Style": "",
    "Producer": "Oliver's",
    "Location": "Ocle Pychard, Herefordshire",
    "ABV (%)": 6
  },
  {
    "Drink Name": "White Jersey (SV)",
    "Style": "",
    "Producer": "Orgasmic Cider Co.",
    "Location": "Great Parton, Herefordshire",
    "ABV (%)": 6
  },
  {
    "Drink Name": "Grey Heron",
    "Style": "",
    "Producer": "Perry's",
    "Location": "Dowlish Wake, Somerset",
    "ABV (%)": 5.5
  },
  {
    "Drink Name": "Vintage",
    "Style": "",
    "Producer": "Perry's",
    "Location": "Dowlish Wake, Somerset",
    "ABV (%)": 7.2
  },
  {
    "Drink Name": "Beetroot & Orange",
    "Style": "",
    "Producer": "Pulp Cider",
    "Location": "Hebden Bridge, Yorkshire",
    "ABV (%)": 4
  },
  {
    "Drink Name": "Rhubarb",
    "Style": "",
    "Producer": "Pulp Cider",
    "Location": "Hebden Bridge, Yorkshire",
    "ABV (%)": 4
  },
  {
    "Drink Name": "Cloudy Rhubarb",
    "Style": "",
    "Producer": "Saxby's Cider",
    "Location": "Farndish, Northamptonshire",
    "ABV (%)": 3.5
  },
  {
    "Drink Name": "Original",
    "Style": "",
    "Producer": "Saxby's Cider",
    "Location": "Farndish, Northamptonshire",
    "ABV (%)": 5
  },
  {
    "Drink Name": "Plum",
    "Style": "",
    "Producer": "Saxby's Cider",
    "Location": "Farndish, Northamptonshire",
    "ABV (%)": 3.8
  },
  {
    "Drink Name": "Traditional",
    "Style": "",
    "Producer": "Saxby's Cider",
    "Location": "Farndish, Northamptonshire",
    "ABV (%)": 5.8
  },
  {
    "Drink Name": "Blood Orange",
    "Style": "",
    "Producer": "Seacider",
    "Location": "Brighton, East Sussex",
    "ABV (%)": 4
  },
  {
    "Drink Name": "Fruit Bat",
    "Style": "",
    "Producer": "Snailsbank",
    "Location": "Bishops Frome, Herefordshire",
    "ABV (%)": 4
  },
  {
    "Drink Name": "Very Perry",
    "Style": "",
    "Producer": "Snailsbank",
    "Location": "Bishops Frome, Herefordshire",
    "ABV (%)": 5
  },
  {
    "Drink Name": "Horsey Girl (Blackcurrant)",
    "Style": "",
    "Producer": "South Downs Cider",
    "Location": "Wilmington, East Sussex",
    "ABV (%)": 4.5
  },
  {
    "Drink Name": "Vanilla",
    "Style": "",
    "Producer": "South Downs Cider",
    "Location": "Wilmington, East Sussex",
    "ABV (%)": 4
  },
  {
    "Drink Name": "Festival Ferret",
    "Style": "",
    "Producer": "Ty Gwyn",
    "Location": "Pontrilas, Herefordshire",
    "ABV (%)": 6.5
  },
  {
    "Drink Name": "Browns",
    "Style": "",
    "Producer": "Whin Hill",
    "Location": "Wells-next-the-Sea, Norfolk",
    "ABV (%)": 5.8
  },
  {
    "Drink Name": "Perry",
    "Style": "",
    "Producer": "Whin Hill",
    "Location": "Wells-next-the-Sea, Norfolk",
    "ABV (%)": 5.4
  },
  {
    "Drink Name": "Apple Slayer",
    "Style": "",
    "Producer": "Cornwall Cider Co.",
    "Location": "Truro, Cornwall",
    "ABV (%)": 5.7
  },
  {
    "Drink Name": "Lyonesse",
    "Style": "",
    "Producer": "Cornwall Cider Co.",
    "Location": "Truro, Cornwall",
    "ABV (%)": 5
  },
  {
    "Drink Name": "Mango, Lime & Ginger",
    "Style": "",
    "Producer": "Cornwall Cider Co.",
    "Location": "Truro, Cornwall",
    "ABV (%)": 4
  },
  {
    "Drink Name": "Rhubarb & Custard",
    "Style": "",
    "Producer": "Cornwall Cider Co.",
    "Location": "Truro, Cornwall",
    "ABV (%)": 4
  },
  {
    "Drink Name": "Blueberry",
    "Style": "",
    "Producer": "Wibblers",
    "Location": "Southminster, Essex",
    "ABV (%)": 4
  },
  {
    "Drink Name": "Death By Wibble",
    "Style": "",
    "Producer": "Wibblers",
    "Location": "Southminster, Essex",
    "ABV (%)": 8
  },
  {
    "Drink Name": "Dengie Medium Dry",
    "Style": "",
    "Producer": "Wibblers",
    "Location": "Southminster, Essex",
    "ABV (%)": 6
  },
  {
    "Drink Name": "Raspberry",
    "Style": "",
    "Producer": "Wibblers",
    "Location": "Southminster, Essex",
    "ABV (%)": 4
  },
  {
    "Drink Name": "Rhubarb & Custard",
    "Style": "",
    "Producer": "Wibblers",
    "Location": "Southminster, Essex",
    "ABV (%)": 4
  }
]
